vnai/__init__.py
vnai/beam/__init__.py
vnai/beam/auth.py
vnai/beam/fundamental.py
vnai/beam/metrics.py
vnai/beam/patching.py
vnai/beam/pulse.py
vnai/beam/quota.py
vnai/beam/sync.py
vnai/flow/__init__.py
vnai/flow/queue.py
vnai/flow/relay.py
vnai/scope/__init__.py
vnai/scope/device.py
vnai/scope/lc_integration.py
vnai/scope/license.py
vnai/scope/profile.py
vnai/scope/promo.py
vnai/scope/state.py
vnai-2.3.9.dist-info/METADATA
vnai-2.3.9.dist-info/WHEEL
vnai-2.3.9.dist-info/top_level.txt
vnai-2.3.9.dist-info/RECORD
