Metadata-Version: 2.4
Name: vnai
Version: 2.3.9
Summary: Vnstock Analytics Interface
Author-email: Vnstock Analytics Team <support@vnstocks.com>
License: proprietary
Project-URL: Homepage, https://vnstocks.com
Classifier: Programming Language :: Python :: 3
Classifier: Operating System :: OS Independent
Classifier: Development Status :: 4 - Beta
Classifier: Intended Audience :: Developers
Classifier: Topic :: Software Development :: Libraries :: Python Modules
Requires-Python: >=3.10
Requires-Dist: requests>=2.25.0
Requires-Dist: psutil>=5.8.0
Requires-Dist: cffi>=1.17.1
Provides-Extra: dev
Requires-Dist: pytest>=6.0.0; extra == "dev"
